MANIFEST.in
README.txt
requirements.txt
run_tests.py
setup.py
django_user_action_confirmation.egg-info/PKG-INFO
django_user_action_confirmation.egg-info/SOURCES.txt
django_user_action_confirmation.egg-info/dependency_links.txt
django_user_action_confirmation.egg-info/not-zip-safe
django_user_action_confirmation.egg-info/requires.txt
django_user_action_confirmation.egg-info/top_level.txt
user_action_confirmation/__init__.py
user_action_confirmation/__init__.pyc
user_action_confirmation/admin.py
user_action_confirmation/models.py
user_action_confirmation/views.py