Metadata-Version: 1.1
Name: django-user-action-confirmation
Version: 0.1.4
Summary: Easy and simple way to confirm user actions in your django projects
Home-page: https://github.com/alekam/django-user-action-confirmation
Author: Alex Kamedov
Author-email: alex@kamedov.ru
License: New BSD License
Keywords: confirm actions,confirmation,user action confirmation
Platform: any
Classifier: Development Status :: 4 - Beta
Classifier: Environment :: Web Environment
Classifier: Framework :: Django
Classifier: Intended Audience :: Developers
Classifier: License :: OSI Approved :: BSD License
Classifier: Operating System :: OS Independent
Classifier: Programming Language :: Python
Classifier: Topic :: Software Development :: Libraries :: Python Modules
Classifier: Topic :: Utilities
